interactions/ext/files/__init__.py
interactions/ext/files/files.py
interactions_files-1.1.5.dist-info/LICENSE
interactions_files-1.1.5.dist-info/METADATA
interactions_files-1.1.5.dist-info/WHEEL
interactions_files-1.1.5.dist-info/top_level.txt
interactions_files-1.1.5.dist-info/RECORD
