Metadata-Version: 2.1
Name: interactions-files
Version: 1.1.5
Summary: An extension library for interactions.py allowing files in interaction responses.
Home-page: https://github.com/interactions-py/files
Author: Jimmy-Blue
Author-email: jimmyblue00@duck.com
License: MIT
Classifier: Programming Language :: Python :: 3.8
Classifier: Development Status :: 4 - Beta
Classifier: License :: OSI Approved :: MIT License
Classifier: Operating System :: OS Independent
License-File: LICENSE
